flask_wifiqr/__init__.py
flask_wifiqr/__main__.py
flask_wifiqr/templates/index.html
flask_wifiqr-0.0.4.dist-info/LICENSE
flask_wifiqr-0.0.4.dist-info/WHEEL
flask_wifiqr-0.0.4.dist-info/METADATA
flask_wifiqr-0.0.4.dist-info/RECORD
