Metadata-Version: 2.1
Name: flask_wifiqr
Version: 0.0.4
Summary: Flask_WifiQR: A simple flask app that serves your wifi password as a QR Code to smartphones
Home-page: https://github.com/fliphess/wifiqr
Author: Flip Hess
Author-email: flip@fliphess.com
Requires-Python: >=3.7
Classifier: License :: OSI Approved :: MIT License
Classifier: Programming Language :: Python :: 3.7
Classifier: Programming Language :: Python :: 3.8
Classifier: Programming Language :: Python :: 3.9
Requires-Dist: Flask
Requires-Dist: Flask-QRcode
Requires-Dist: pytest ; extra == "test"
Requires-Dist: pytest-cov ; extra == "test"
Requires-Dist: pyproject-flake8 ; extra == "test"
Provides-Extra: test
